pyramid_ogcapi/__init__.py
pyramid_ogcapi/json2html.py
pyramid_ogcapi/links.py
pyramid_ogcapi/py.typed
pyramid_ogcapi/templates/default.mako
pyramid_ogcapi-0.2.1.dist-info/LICENSE
pyramid_ogcapi-0.2.1.dist-info/METADATA
pyramid_ogcapi-0.2.1.dist-info/WHEEL
pyramid_ogcapi-0.2.1.dist-info/RECORD
