Metadata-Version: 2.1
Name: pyramid-ogcapi
Version: 0.2.1
Summary: Build pyramid routes, provide template for user html pages
Home-page: https://github.com/camptocamp/pyramid-ogcapi
License: BSD-2-Clause
Keywords: ogcapi,openapi,pyramid
Author: Stéphane Brunner
Author-email: stephane.brunner@camptocamp.com
Requires-Python: >=3.9,<3.12
Classifier: Development Status :: 4 - Beta
Classifier: Environment :: Web Environment
Classifier: Intended Audience :: Developers
Classifier: License :: OSI Approved :: BSD License
Classifier: Operating System :: OS Independent
Classifier: Programming Language :: Python
Classifier: Programming Language :: Python :: 3
Classifier: Programming Language :: Python :: 3.9
Classifier: Programming Language :: Python :: 3.10
Classifier: Programming Language :: Python :: 3.11
Classifier: Typing :: Typed
Provides-Extra: application
Requires-Dist: c2cwsgiutils[oauth2,standard,test-images] ; extra == "application"
Requires-Dist: openapi-core
Requires-Dist: pyramid-mako
Requires-Dist: pyramid-openapi3
Project-URL: Repository, https://github.com/camptocamp/pyramid-ogcapi
